noob/__init__.py
noob/__main__.py
noob/package.py
noob/util.py
noob/version.py
homebrew_npm_noob-0.3.dist-info/COPYING
homebrew_npm_noob-0.3.dist-info/METADATA
homebrew_npm_noob-0.3.dist-info/WHEEL
homebrew_npm_noob-0.3.dist-info/entry_points.txt
homebrew_npm_noob-0.3.dist-info/top_level.txt
homebrew_npm_noob-0.3.dist-info/RECORD
