Metadata-Version: 2.1
Name: homebrew-npm-noob
Version: 0.3
Summary: Generate Homebrew formulae for npm packages
Home-page: https://github.com/zmwangx/homebrew-npm-noob
Author: Zhiming Wang
Author-email: pypi@zhimingwang.org
License: MIT
Keywords: homebrew formula node npm
Platform: UNKNOWN
Classifier: Development Status :: 5 - Production/Stable
Classifier: Intended Audience :: Developers
Classifier: License :: OSI Approved :: MIT License
Classifier: Programming Language :: Python :: 3
Classifier: Programming Language :: Python :: 3.3
Classifier: Programming Language :: Python :: 3.4
Classifier: Programming Language :: Python :: 3.5
Classifier: Programming Language :: Python :: 3.6
Classifier: Programming Language :: Python :: 3.7
Classifier: Programming Language :: Python :: 3.8
Classifier: Programming Language :: Python :: 3.9
Classifier: Programming Language :: Python :: 3 :: Only
Classifier: Topic :: Software Development :: Code Generators
Requires-Dist: jinja2
Requires-Dist: requests
Provides-Extra: dev
Requires-Dist: black ; extra == 'dev'
Provides-Extra: test
Requires-Dist: pytest ; extra == 'test'
